Workbook

Sheet Assumptions
A1: ShieldAI — Unit Economics & Pricing Model
A2: Every blue cell is an input you can change. Black cells are formulas. Yellow = the assumptions that most affect the answer.
A3: Sources: cost inputs derived from the ShieldAI codebase (generators.js, mastermindRoutes.js); market inputs from the 2026 Business Plan and cited competitor research.
A5: PRICING TIERS
A6: Tier | B6: Price/mo ($) | C6: Engineer hrs/mo | D6: AI cost/mo ($) | E6: Support hrs/mo | F6: Notes
A7: Free | B7: 0 | C7: 0 | D7: 2 | E7: 0.1 | F7: Assessment + score only. Acquisition, not revenue.
A8: Starter | B8: 159 | C8: 0 | D8: 6 | E8: 0.25 | F8: Full program, policies, 4 control-mapped frameworks. No human time.
A9: Growth | B9: 349 | C9: 0.5 | D9: 9 | E9: 0.5 | F9: Starter + monitoring agent, CVE/breach intel, quarterly review.
A10: Guided | B10: 699 | C10: 2 | D10: 12 | E10: 1 | F10: Growth + engineer review, compliance tracking, monthly check-in.
A11: Managed | B11: 1950 | C11: 8 | D11: 18 | E11: 2 | F11: Engineer runs the program end-to-end. Qualified Individual for FTC.
A13: COST INPUTS
A14: Fully loaded engineer cost | B14: 140000 | C14: Per year, incl. benefits/overhead. Business Plan §5.3.
A15: Engineer productive hrs/yr | B15: 1600 | C15: 2,080 gross less PTO, admin, training, ramp.
A16: Engineer cost / hour | B16: =B14/B15 -> 87.5 | C16: Computed: cost / productive hours
A17: Support cost / hour | B17: 35 | C17: Blended CS/onboarding rate.
A18: Infrastructure / client / mo | B18: 3 | C18: Railway, storage, bandwidth at scale.
A19: Payment processing | B19: 0.029 | C19: Stripe 2.9% + $0.30; the fixed fee matters at low ARPU.
A20: Payment fixed fee | B20: 0.3 | C20: Per transaction.
A22: ACQUISITION & RETENTION
A23: THE PLAN HAS NO CAC. These are the levers that decide whether $159 works — they need real data, not estimates.
A24: Blended CAC — self-serve | B24: 400 | C24: Paid + content + tooling per paying Starter/Growth client. UNVALIDATED.
A25: Blended CAC — assisted | B25: 1800 | C25: Guided/Managed: includes sales time. UNVALIDATED.
A26: Free → paid conversion | B26: 0.08 | C26: Of free assessments that become paying. UNVALIDATED.
A27: Monthly churn — self-serve | B27: 0.045 | C27: 4.5%/mo ≈ 42%/yr. SMB self-serve churns hard.
A28: Monthly churn — assisted | B28: 0.015 | C28: 1.5%/mo ≈ 17%/yr. Human relationship retains.
A29: Gross margin target | B29: 0.75 | C29: Business Plan claims ~75% at Managed.
A30: Max acceptable CAC payback | B30: 12 | C30: Months. Above ~18 the model needs a lot of capital.
A32: AI COST BUILD-UP (from the actual codebase, not a guess)
A33: Program sections generated | B33: 10 | C33: generators.js: riskOverview…execReport.
A34: Avg tokens per section (in+out) | B34: 6000 | C34: ~2k prompt + ~4k completion.
A35: Policies generated per client | B35: 6 | C35: Of 40 in policyCatalog.js; most clients use a subset.
A36: Avg tokens per policy | B36: 5000 | C36: Long-form structured output.
A37: Mastermind msgs / client / mo | B37: 8 | C37: mastermindRoutes.js: 1.2k–2k max_tokens per call.
A38: Avg tokens per Mastermind msg | B38: 4000 | C38: Incl. conversation history resent each turn.
A39: Blended $ per 1M tokens | B39: 6 | C39: Mixed input/output across the provider fallback chain.
A40: Program regenerations / yr | B40: 2 | C40: Reassessment cadence.
A42: Onboarding AI cost (one-time) | B42: =((B33*B34)+(B35*B36))/1000000*B39 -> 0.54 | C42: Full program + policies at signup.
A43: Ongoing AI cost / client / mo | B43: =(B37*B38)/1000000*B39+(B42*B40/12) -> 0.282 | C43: Mastermind + amortised regeneration. Compare to the plan's $15 assumption.

Sheet Unit Economics
A1: Unit Economics by Tier
A2: Per-client, per-month. LTV uses gross margin (not revenue) — an LTV built on revenue flatters every SaaS model.
A4: Metric | B4: Free | C4: Starter | D4: Growth | E4: Guided | F4: Managed
A5: Price / month | B5: =Assumptions!B7 -> 0 | C5: =Assumptions!B8 -> 159 | D5: =Assumptions!B9 -> 349 | E5: =Assumptions!B10 -> 699 | F5: =Assumptions!B11 -> 1950
A7: Engineer cost | B7: =Assumptions!C7*Assumptions!$B$16 -> 0 | C7: =Assumptions!C8*Assumptions!$B$16 -> 0 | D7: =Assumptions!C9*Assumptions!$B$16 -> 43.75 | E7: =Assumptions!C10*Assumptions!$B$16 -> 175 | F7: =Assumptions!C11*Assumptions!$B$16 -> 700
A8: Support cost | B8: =Assumptions!E7*Assumptions!$B$17 -> 3.5 | C8: =Assumptions!E8*Assumptions!$B$17 -> 8.75 | D8: =Assumptions!E9*Assumptions!$B$17 -> 17.5 | E8: =Assumptions!E10*Assumptions!$B$17 -> 35 | F8: =Assumptions!E11*Assumptions!$B$17 -> 70
A9: AI cost | B9: =Assumptions!D7 -> 2 | C9: =Assumptions!D8 -> 6 | D9: =Assumptions!D9 -> 9 | E9: =Assumptions!D10 -> 12 | F9: =Assumptions!D11 -> 18
A10: Infrastructure | B10: =Assumptions!$B$18 -> 3 | C10: =Assumptions!$B$18 -> 3 | D10: =Assumptions!$B$18 -> 3 | E10: =Assumptions!$B$18 -> 3 | F10: =Assumptions!$B$18 -> 3
A11: Payment processing | B11: =IF(Assumptions!B7=0,0,Assumptions!B7*Assumptions!$B$19+Assumptions!$B$20) -> 0 | C11: =IF(Assumptions!B8=0,0,Assumptions!B8*Assumptions!$B$19+Assumptions!$B$20) -> 4.911 | D11: =IF(Assumptions!B9=0,0,Assumptions!B9*Assumptions!$B$19+Assumptions!$B$20) -> 10.421 | E11: =IF(Assumptions!B10=0,0,Assumptions!B10*Assumptions!$B$19+Assumptions!$B$20) -> 20.571 | F11: =IF(Assumptions!B11=0,0,Assumptions!B11*Assumptions!$B$19+Assumptions!$B$20) -> 56.85
A12: Total COGS | B12: =SUM(B7:B11) -> 8.5 | C12: =SUM(C7:C11) -> 22.661 | D12: =SUM(D7:D11) -> 83.671 | E12: =SUM(E7:E11) -> 245.571 | F12: =SUM(F7:F11) -> 847.85
A14: Gross profit / mo | B14: =B5-B12 -> -8.5 | C14: =C5-C12 -> 136.339 | D14: =D5-D12 -> 265.329 | E14: =E5-E12 -> 453.429 | F14: =F5-F12 -> 1102.15
A15: Gross margin % | B15: =IF(B5=0,0,B14/B5) -> 0 | C15: =IF(C5=0,0,C14/C5) -> 0.85747799 | D15: =IF(D5=0,0,D14/D5) -> 0.76025501 | E15: =IF(E5=0,0,E14/E5) -> 0.6486824 | F15: =IF(F5=0,0,F14/F5) -> 0.56520513
A17: CAC | B17: =0 -> 0 | C17: =Assumptions!$B$24 -> 400 | D17: =Assumptions!$B$24 -> 400 | E17: =Assumptions!$B$25 -> 1800 | F17: =Assumptions!$B$25 -> 1800
A18: Monthly churn | B18: =Assumptions!$B$27 -> 0.045 | C18: =Assumptions!$B$27 -> 0.045 | D18: =Assumptions!$B$27 -> 0.045 | E18: =Assumptions!$B$28 -> 0.015 | F18: =Assumptions!$B$28 -> 0.015
A19: Avg lifetime (months) | B19: =IF(B18=0,0,1/B18) -> 22.222222 | C19: =IF(C18=0,0,1/C18) -> 22.222222 | D19: =IF(D18=0,0,1/D18) -> 22.222222 | E19: =IF(E18=0,0,1/E18) -> 66.666667 | F19: =IF(F18=0,0,1/F18) -> 66.666667
A20: LTV (gross-margin based) | B20: =B14*B19 -> -188.88889 | C20: =C14*C19 -> 3029.7556 | D20: =D14*D19 -> 5896.2 | E20: =E14*E19 -> 30228.6 | F20: =F14*F19 -> 73476.667
A21: LTV : CAC | B21: =IF(B17=0,0,B20/B17) -> 0 | C21: =IF(C17=0,0,C20/C17) -> 7.5743889 | D21: =IF(D17=0,0,D20/D17) -> 14.7405 | E21: =IF(E17=0,0,E20/E17) -> 16.793667 | F21: =IF(F17=0,0,F20/F17) -> 40.82037
A22: CAC payback (months) | B22: =IF(B14<=0,999,B17/B14) -> 999 | C22: =IF(C14<=0,999,C17/C14) -> 2.9338634 | D22: =IF(D14<=0,999,D17/D14) -> 1.5075623 | E22: =IF(E14<=0,999,E17/E14) -> 3.9697505 | F22: =IF(F14<=0,999,F17/F14) -> 1.6331715
A24: VERDICT | B24: =IF(B5=0,"Acquisition",IF(B14<=0,"LOSS-MAKING",IF(AND(B21>=3,B22<=Assumptions!$B$30),"HEALTHY",IF(B21>=1.5,"MARGINAL","UNVIABLE")))) -> Acquisition | C24: =IF(C5=0,"Acquisition",IF(C14<=0,"LOSS-MAKING",IF(AND(C21>=3,C22<=Assumptions!$B$30),"HEALTHY",IF(C21>=1.5,"MARGINAL","UNVIABLE")))) -> HEALTHY | D24: =IF(D5=0,"Acquisition",IF(D14<=0,"LOSS-MAKING",IF(AND(D21>=3,D22<=Assumptions!$B$30),"HEALTHY",IF(D21>=1.5,"MARGINAL","UNVIABLE")))) -> HEALTHY | E24: =IF(E5=0,"Acquisition",IF(E14<=0,"LOSS-MAKING",IF(AND(E21>=3,E22<=Assumptions!$B$30),"HEALTHY",IF(E21>=1.5,"MARGINAL","UNVIABLE")))) -> HEALTHY | F24: =IF(F5=0,"Acquisition",IF(F14<=0,"LOSS-MAKING",IF(AND(F21>=3,F22<=Assumptions!$B$30),"HEALTHY",IF(F21>=1.5,"MARGINAL","UNVIABLE")))) -> HEALTHY
A26: Benchmarks: LTV:CAC ≥ 3.0x is the standard bar. CAC payback ≤ 12 months keeps the business fundable without heavy capital.
A27: Note: 'Free' shows Acquisition — its cost is real and is carried by the conversion rate on the Assumptions tab.

Sheet Price Finder
A1: What price does the model actually support?
A2: Solves the question the plan doesn't: at a given CAC and churn, what is the MINIMUM price for a healthy business?
A4: Inputs
A5: CAC | B5: =Assumptions!B24 -> 400 | C5: Self-serve blended.
A6: Monthly churn | B6: =Assumptions!B27 -> 0.045 | C6: Self-serve.
A7: Target LTV:CAC | B7: 3 | C7: The standard bar.
A8: Target payback (months) | B8: =Assumptions!B30 -> 12
A9: Non-price COGS / mo | B9: =Assumptions!D8+Assumptions!$B$18+Assumptions!E8*Assumptions!$B$17 -> 17.75 | C9: AI + infra + support at Starter.
A11: Required outcomes
A12: Lifetime (months) | B12: =1/B6 -> 22.222222
A13: Gross profit needed (LTV:CAC) | B13: =B5*B7/B12 -> 54
A14: Gross profit needed (payback) | B14: =B5/B8 -> 33.333333
A15: Binding constraint | B15: =IF(B13>B14,"LTV:CAC","Payback") -> LTV:CAC
A16: Gross profit needed / mo | B16: =MAX(B13,B14) -> 54
A17: MINIMUM VIABLE PRICE | B17: =(B16+Assumptions!$B$20+B9)/(1-Assumptions!$B$19) -> 74.201854
A18: Your proposed Starter price | B18: =Assumptions!B8 -> 159
A19: Headroom vs. minimum | B19: =B18-B17 -> 84.798146
A20: Verdict | B20: =IF(B18>=B17,"WORKS at this CAC/churn","TOO LOW — raise price, cut CAC, or cut churn") -> WORKS at this CAC/churn
A22: LTV:CAC — Starter price (rows) vs. CAC (columns)
A23: Price \ CAC | B23: 200 | C23: 300 | D23: 400 | E23: 600 | F23: 800 | G23: 1200
A24: 99 | B24: =(($A24-($A24*Assumptions!$B$19+Assumptions!$B$20)-$B$9)*$B$12)/B$23 -> 8.6754444 | C24: =(($A24-($A24*Assumptions!$B$19+Assumptions!$B$20)-$B$9)*$B$12)/C$23 -> 5.7836296 | D24: =(($A24-($A24*Assumptions!$B$19+Assumptions!$B$20)-$B$9)*$B$12)/D$23 -> 4.3377222 | E24: =(($A24-($A24*Assumptions!$B$19+Assumptions!$B$20)-$B$9)*$B$12)/E$23 -> 2.8918148 | F24: =(($A24-($A24*Assumptions!$B$19+Assumptions!$B$20)-$B$9)*$B$12)/F$23 -> 2.1688611 | G24: =(($A24-($A24*Assumptions!$B$19+Assumptions!$B$20)-$B$9)*$B$12)/G$23 -> 1.4459074
A25: 129 | B25: =(($A25-($A25*Assumptions!$B$19+Assumptions!$B$20)-$B$9)*$B$12)/B$23 -> 11.912111 | C25: =(($A25-($A25*Assumptions!$B$19+Assumptions!$B$20)-$B$9)*$B$12)/C$23 -> 7.9414074 | D25: =(($A25-($A25*Assumptions!$B$19+Assumptions!$B$20)-$B$9)*$B$12)/D$23 -> 5.9560556 | E25: =(($A25-($A25*Assumptions!$B$19+Assumptions!$B$20)-$B$9)*$B$12)/E$23 -> 3.9707037 | F25: =(($A25-($A25*Assumptions!$B$19+Assumptions!$B$20)-$B$9)*$B$12)/F$23 -> 2.9780278 | G25: =(($A25-($A25*Assumptions!$B$19+Assumptions!$B$20)-$B$9)*$B$12)/G$23 -> 1.9853519
A26: 159 | B26: =(($A26-($A26*Assumptions!$B$19+Assumptions!$B$20)-$B$9)*$B$12)/B$23 -> 15.148778 | C26: =(($A26-($A26*Assumptions!$B$19+Assumptions!$B$20)-$B$9)*$B$12)/C$23 -> 10.099185 | D26: =(($A26-($A26*Assumptions!$B$19+Assumptions!$B$20)-$B$9)*$B$12)/D$23 -> 7.5743889 | E26: =(($A26-($A26*Assumptions!$B$19+Assumptions!$B$20)-$B$9)*$B$12)/E$23 -> 5.0495926 | F26: =(($A26-($A26*Assumptions!$B$19+Assumptions!$B$20)-$B$9)*$B$12)/F$23 -> 3.7871944 | G26: =(($A26-($A26*Assumptions!$B$19+Assumptions!$B$20)-$B$9)*$B$12)/G$23 -> 2.5247963
A27: 199 | B27: =(($A27-($A27*Assumptions!$B$19+Assumptions!$B$20)-$B$9)*$B$12)/B$23 -> 19.464333 | C27: =(($A27-($A27*Assumptions!$B$19+Assumptions!$B$20)-$B$9)*$B$12)/C$23 -> 12.976222 | D27: =(($A27-($A27*Assumptions!$B$19+Assumptions!$B$20)-$B$9)*$B$12)/D$23 -> 9.7321667 | E27: =(($A27-($A27*Assumptions!$B$19+Assumptions!$B$20)-$B$9)*$B$12)/E$23 -> 6.4881111 | F27: =(($A27-($A27*Assumptions!$B$19+Assumptions!$B$20)-$B$9)*$B$12)/F$23 -> 4.8660833 | G27: =(($A27-($A27*Assumptions!$B$19+Assumptions!$B$20)-$B$9)*$B$12)/G$23 -> 3.2440556
A28: 249 | B28: =(($A28-($A28*Assumptions!$B$19+Assumptions!$B$20)-$B$9)*$B$12)/B$23 -> 24.858778 | C28: =(($A28-($A28*Assumptions!$B$19+Assumptions!$B$20)-$B$9)*$B$12)/C$23 -> 16.572519 | D28: =(($A28-($A28*Assumptions!$B$19+Assumptions!$B$20)-$B$9)*$B$12)/D$23 -> 12.429389 | E28: =(($A28-($A28*Assumptions!$B$19+Assumptions!$B$20)-$B$9)*$B$12)/E$23 -> 8.2862593 | F28: =(($A28-($A28*Assumptions!$B$19+Assumptions!$B$20)-$B$9)*$B$12)/F$23 -> 6.2146944 | G28: =(($A28-($A28*Assumptions!$B$19+Assumptions!$B$20)-$B$9)*$B$12)/G$23 -> 4.1431296
A29: 299 | B29: =(($A29-($A29*Assumptions!$B$19+Assumptions!$B$20)-$B$9)*$B$12)/B$23 -> 30.253222 | C29: =(($A29-($A29*Assumptions!$B$19+Assumptions!$B$20)-$B$9)*$B$12)/C$23 -> 20.168815 | D29: =(($A29-($A29*Assumptions!$B$19+Assumptions!$B$20)-$B$9)*$B$12)/D$23 -> 15.126611 | E29: =(($A29-($A29*Assumptions!$B$19+Assumptions!$B$20)-$B$9)*$B$12)/E$23 -> 10.084407 | F29: =(($A29-($A29*Assumptions!$B$19+Assumptions!$B$20)-$B$9)*$B$12)/F$23 -> 7.5633056 | G29: =(($A29-($A29*Assumptions!$B$19+Assumptions!$B$20)-$B$9)*$B$12)/G$23 -> 5.0422037
A30: 349 | B30: =(($A30-($A30*Assumptions!$B$19+Assumptions!$B$20)-$B$9)*$B$12)/B$23 -> 35.647667 | C30: =(($A30-($A30*Assumptions!$B$19+Assumptions!$B$20)-$B$9)*$B$12)/C$23 -> 23.765111 | D30: =(($A30-($A30*Assumptions!$B$19+Assumptions!$B$20)-$B$9)*$B$12)/D$23 -> 17.823833 | E30: =(($A30-($A30*Assumptions!$B$19+Assumptions!$B$20)-$B$9)*$B$12)/E$23 -> 11.882556 | F30: =(($A30-($A30*Assumptions!$B$19+Assumptions!$B$20)-$B$9)*$B$12)/F$23 -> 8.9119167 | G30: =(($A30-($A30*Assumptions!$B$19+Assumptions!$B$20)-$B$9)*$B$12)/G$23 -> 5.9412778
A32: Green ≥3.0x healthy · Amber 1.5–3.0x marginal · Red <1.5x unviable. Read down your CAC column to find the price that clears 3.0x.

Sheet 3-Year Model
A1: Three-Year Projection
A2: Client counts are inputs (blue). Everything else computes. Compare the Net Margin row against the Business Plan's ~75% gross-margin claim.
A4: Metric | B4: Year 1 | C4: Year 2 | D4: Year 3
A5: CLIENTS (end of year)
A6: Free | B6: 600 | C6: 2000 | D6: 5000
A7: Starter | B7: 120 | C7: 400 | D7: 1000
A8: Growth | B8: 40 | C8: 160 | D8: 450
A9: Guided | B9: 30 | C9: 120 | D9: 350
A10: Managed | B10: 20 | C10: 90 | D10: 260
A11: Total paying clients | B11: =SUM(B7:B10) -> 210 | C11: =SUM(C7:C10) -> 770 | D11: =SUM(D7:D10) -> 2060
A13: REVENUE
A14: Starter ARR | B14: =B7*Assumptions!$B$8*12 -> 228960 | C14: =C7*Assumptions!$B$8*12 -> 763200 | D14: =D7*Assumptions!$B$8*12 -> 1908000
A15: Growth ARR | B15: =B8*Assumptions!$B$9*12 -> 167520 | C15: =C8*Assumptions!$B$9*12 -> 670080 | D15: =D8*Assumptions!$B$9*12 -> 1884600
A16: Guided ARR | B16: =B9*Assumptions!$B$10*12 -> 251640 | C16: =C9*Assumptions!$B$10*12 -> 1006560 | D16: =D9*Assumptions!$B$10*12 -> 2935800
A17: Managed ARR | B17: =B10*Assumptions!$B$11*12 -> 468000 | C17: =C10*Assumptions!$B$11*12 -> 2106000 | D17: =D10*Assumptions!$B$11*12 -> 6084000
A18: Total ARR | B18: =SUM(B14:B17) -> 1116120 | C18: =SUM(C14:C17) -> 4545840 | D18: =SUM(D14:D17) -> 12812400
A20: COGS
A21: Engineer hours needed / yr | B21: =(B6*Assumptions!$C$7+B7*Assumptions!$C$8+B8*Assumptions!$C$9+B9*Assumptions!$C$10+B10*Assumptions!$C$11)*12 -> 2880 | C21: =(C6*Assumptions!$C$7+C7*Assumptions!$C$8+C8*Assumptions!$C$9+C9*Assumptions!$C$10+C10*Assumptions!$C$11)*12 -> 12480 | D21: =(D6*Assumptions!$C$7+D7*Assumptions!$C$8+D8*Assumptions!$C$9+D9*Assumptions!$C$10+D10*Assumptions!$C$11)*12 -> 36060
A22: Engineers required | B22: =ROUNDUP(B21/Assumptions!$B$15,0) -> 2 | C22: =ROUNDUP(C21/Assumptions!$B$15,0) -> 8 | D22: =ROUNDUP(D21/Assumptions!$B$15,0) -> 23
A23: Engineer cost | B23: =B22*Assumptions!$B$14 -> 280000 | C23: =C22*Assumptions!$B$14 -> 1120000 | D23: =D22*Assumptions!$B$14 -> 3220000
A24: AI + infrastructure | B24: =(B6*(Assumptions!$D$7+Assumptions!$B$18)+B7*(Assumptions!$D$8+Assumptions!$B$18)+B8*(Assumptions!$D$9+Assumptions!$B$18)+B9*(Assumptions!$D$10+Assumptions!$B$18)+B10*(Assumptions!$D$11+Assumptions!$B$18))*12 -> 65160 | C24: =(C6*(Assumptions!$D$7+Assumptions!$B$18)+C7*(Assumptions!$D$8+Assumptions!$B$18)+C8*(Assumptions!$D$9+Assumptions!$B$18)+C9*(Assumptions!$D$10+Assumptions!$B$18)+C10*(Assumptions!$D$11+Assumptions!$B$18))*12 -> 230520 | D24: =(D6*(Assumptions!$D$7+Assumptions!$B$18)+D7*(Assumptions!$D$8+Assumptions!$B$18)+D8*(Assumptions!$D$9+Assumptions!$B$18)+D9*(Assumptions!$D$10+Assumptions!$B$18)+D10*(Assumptions!$D$11+Assumptions!$B$18))*12 -> 601320
A25: Support | B25: =(B6*Assumptions!$E$7+B7*Assumptions!$E$8+B8*Assumptions!$E$9+B9*Assumptions!$E$10+B10*Assumptions!$E$11)*12*Assumptions!$B$17 -> 75600 | C25: =(C6*Assumptions!$E$7+C7*Assumptions!$E$8+C8*Assumptions!$E$9+C9*Assumptions!$E$10+C10*Assumptions!$E$11)*12*Assumptions!$B$17 -> 285600 | D25: =(D6*Assumptions!$E$7+D7*Assumptions!$E$8+D8*Assumptions!$E$9+D9*Assumptions!$E$10+D10*Assumptions!$E$11)*12*Assumptions!$B$17 -> 774900
A26: Payment processing | B26: =B18*Assumptions!$B$19+B11*12*Assumptions!$B$20 -> 33123.48 | C26: =C18*Assumptions!$B$19+C11*12*Assumptions!$B$20 -> 134601.36 | D26: =D18*Assumptions!$B$19+D11*12*Assumptions!$B$20 -> 378975.6
A27: Total COGS | B27: =SUM(B23:B26) -> 453883.48 | C27: =SUM(C23:C26) -> 1770721.4 | D27: =SUM(D23:D26) -> 4975195.6
A29: Gross profit | B29: =B18-B27 -> 662236.52 | C29: =C18-C27 -> 2775118.6 | D29: =D18-D27 -> 7837204.4
A30: Gross margin % | B30: =IF(B18=0,0,B29/B18) -> 0.5933381 | C30: =IF(C18=0,0,C29/C18) -> 0.61047433 | D30: =IF(D18=0,0,D29/D18) -> 0.61168902
A32: ACQUISITION COST (below the gross-margin line)
A33: New clients added | B33: =B11 -> 210 | C33: =C11-B11+B11*Assumptions!$B$27*12 -> 673.4 | D33: =D11-C11+C11*Assumptions!$B$27*12 -> 1705.8
A34: Sales & marketing (CAC) | B34: =B33*Assumptions!$B$24 -> 84000 | C34: =C33*Assumptions!$B$24 -> 269360 | D34: =D33*Assumptions!$B$24 -> 682320
A36: Contribution after CAC | B36: =B29-B34 -> 578236.52 | C36: =C29-C34 -> 2505758.6 | D36: =D29-D34 -> 7154884.4
A37: Net margin after CAC % | B37: =IF(B18=0,0,B36/B18) -> 0.51807738 | C37: =IF(C18=0,0,C36/C18) -> 0.55122016 | D37: =IF(D18=0,0,D36/D18) -> 0.55843436
A39: Blended ARPU / month | B39: =IF(B11=0,0,B18/B11/12) -> 442.90476 | C39: =IF(C11=0,0,C18/C11/12) -> 491.97403 | D39: =IF(D11=0,0,D18/D11/12) -> 518.30097
A40: ARR per engineer | B40: =IF(B22=0,0,B18/B22) -> 558060 | C40: =IF(C22=0,0,C18/C22) -> 568230 | D40: =IF(D22=0,0,D18/D22) -> 557060.87
A42: Gross margin % is BEFORE customer acquisition. Net margin after CAC is the number that determines whether the business funds itself.
A43: The Business Plan's ~75% figure is a gross margin at the Managed tier only — not a company-wide net margin. Both are shown here so the difference is visible.
